{
  "$schema": "../node_modules/@tauri-apps/cli/schema.json",
  "build": {
    "beforeBuildCommand": "npm run build",
    "beforeDevCommand": "npm run start",
    "devPath": "http://localhost:8080/",
    "distDir": "../build/prod"
  },
  "package": {
    "productName": "CyberChef",
    "version": "../package.json"
  },
  "tauri": {
    "allowlist": {
      "all": false
    },
    "bundle": {
      "active": true,
      "category": "DeveloperTool",
      "copyright": "",
      "deb": {
        "depends": []
      },
      "externalBin": [],
      "icon": [
        "icons/32x32.png",
        "icons/128x128.png",
        "icons/128x128@2x.png",
        "icons/icon.icns",
        "icons/icon.ico"
      ],
      "identifier": "net.zanreal.cyberchef",
      "longDescription": "",
      "macOS": {
        "entitlements": null,
        "exceptionDomain": "",
        "frameworks": [],
        "providerShortName": null,
        "signingIdentity": null
      },
      "resources": [],
      "shortDescription": "",
      "targets": "all",
      "windows": {
        "certificateThumbprint": null,
        "digestAlgorithm": "sha256",
        "timestampUrl": ""
      }
    },
    "security": {
      "csp": null
    },
    "updater": {
      "active": false
    },
    "windows": [
      {
        "fullscreen": false,
        "height": 600,
        "resizable": true,
        "title": "CyberChef",
        "width": 800
      }
    ]
  }
}
